MANIFEST.in
README.txt
setup.py
c2/__init__.py
c2.app.zipdownload.egg-info/PKG-INFO
c2.app.zipdownload.egg-info/SOURCES.txt
c2.app.zipdownload.egg-info/dependency_links.txt
c2.app.zipdownload.egg-info/entry_points.txt
c2.app.zipdownload.egg-info/namespace_packages.txt
c2.app.zipdownload.egg-info/not-zip-safe
c2.app.zipdownload.egg-info/requires.txt
c2.app.zipdownload.egg-info/top_level.txt
c2/app/__init__.py
c2/app/zipdownload/__init__.py
c2/app/zipdownload/configure.zcml
c2/app/zipdownload/event.py
c2/app/zipdownload/interfaces.py
c2/app/zipdownload/version.txt
c2/app/zipdownload/browser/__init__.py
c2/app/zipdownload/browser/configure.zcml
c2/app/zipdownload/browser/download.py
c2/app/zipdownload/controlpanel/__init__.py
c2/app/zipdownload/controlpanel/configure.zcml
c2/app/zipdownload/controlpanel/interfaces.py
c2/app/zipdownload/controlpanel/main.py
c2/app/zipdownload/profiles/default/actions.xml
c2/app/zipdownload/profiles/default/controlpanel.xml
c2/app/zipdownload/profiles/default/metadata.xml
c2/app/zipdownload/profiles/default/registry.xml
c2/app/zipdownload/tests/__init__.py
c2/app/zipdownload/tests/test_setup.py
docs/HISTORY.txt
docs/INSTALL.txt
docs/LICENSE.GPL
docs/LICENSE.txt