Metadata-Version: 1.0
Name: c2.app.zipdownload
Version: 1.0b4
Summary: This product is zip download of Plone content
Home-page: http://www.cmscom.jp
Author: Manabu TERADA
Author-email: terada@cmscom.jp
License: GPL
Keywords: plone download file zip
Platform: UNKNOWN
Classifier: Framework :: Plone
Classifier: Programming Language :: Python
